Metadata-Version: 2.1
Name: networkconfigutility
Version: 1.0.3
Summary: Utility for pushing configuration data to network devices and retrieving state data
Home-page: UNKNOWN
Author: naonder
Author-email: nate.a.onder@gmail.com
License: MIT
Platform: UNKNOWN
